[
    {
        "id": "f579b0ec-4506-41a7-9ca6-806f0b2f51dd",
        "name": "ankit",
        "email": "ankit@gmail.com",
        "comment": "Hi this is a ankit"
    },
    {
        "id": "373a399c-232b-458e-a10f-1990ee2980d6",
        "name": "dev",
        "email": "dev@gmail.com",
        "comment": "Hi this is a dev"
    },
    {
        "id": "1d2e4781-6b29-47d2-abb2-90b204a832d7",
        "name": "dev",
        "email": "dev@gdff.com",
        "comment": "Hi this is a dev"
    },
    {
        "id": "f7dac7cd-618f-44c4-80c7-83c0e07992bb",
        "name": "dev",
        "email": "d_ev@gnail.com",
        "comment": "Hi this is a dev"
    },
    {
        "id": "76add4eb-0516-4a8d-97f4-8fe2426d28bc",
        "name": "dev",
        "email": "khushi@gnail.com",
        "comment": "Hi this is a khushi"
    },
    {
        "id": "9bc9df78-1eb0-47bd-80bb-ac612caf2686",
        "name": "dev",
        "email": "rehul@gnail.com",
        "comment": "Hi this is a khushi"
    }
]